bungee
libbungee.so
bungee_python/__init__.py
bungee_python/bungee.cpython-39-x86_64-linux-gnu.so
bungee_python/bungee.pyi
bungee_python/libbungee.so
bungee_python/py.typed
include/bungee/Bungee.h
include/bungee/CommandLine.h
include/bungee/Push.h
include/bungee/Stream.h
pkgconfig/libbungee.pc
sample/cxxopts.hpp
sample/main.cpp
bungee_python-0.2.1.dist-info/METADATA
bungee_python-0.2.1.dist-info/WHEEL
bungee_python-0.2.1.dist-info/RECORD
bungee_python-0.2.1.dist-info/licenses/LICENSE
