Metadata-Version: 2.2
Name: bungee-python
Version: 0.2.1
Summary: Python bindings for the Bungee time/pitch stretching library
License: MPL-2.0
Requires-Python: >=3.9
